{
  "__type__": "sp.SkeletonData",
  "_name": "sjgx2",
  "_objFlags": 0,
  "_native": "",
  "_skeletonJson": {
    "skeleton": {
      "hash": "n7tpHu8RBVCAoHmMpiiqY41nl9E",
      "spine": "3.8.99",
      "x": -331.64,
      "y": -140,
      "width": 491.89,
      "height": 475.23
    },
    "bones": [
      {
        "name": "root"
      },
      {
        "name": "shengjiel",
        "parent": "root"
      },
      {
        "name": "bone",
        "parent": "shengjiel",
        "x": -6.32,
        "y": -0.91
      },
      {
        "name": "bone2",
        "parent": "bone",
        "x": -77.34,
        "y": 78.49
      },
      {
        "name": "bone22",
        "parent": "bone",
        "x": -43.99,
        "y": 39.19
      },
      {
        "name": "bone23",
        "parent": "bone22",
        "x": -32.97,
        "y": 39.77
      },
      {
        "name": "bone3",
        "parent": "bone22",
        "x": -32.97,
        "y": 39.77
      },
      {
        "name": "juguang",
        "parent": "bone",
        "x": -45.31,
        "y": 40.18
      },
      {
        "name": "bone24",
        "parent": "juguang",
        "x": -256.01,
        "y": 59.43,
        "scaleX": 0.8,
        "scaleY": 0.8
      },
      {
        "name": "bone25",
        "parent": "juguang",
        "x": 187.88,
        "y": 74.95,
        "scaleX": 0.8,
        "scaleY": 0.8
      },
      {
        "name": "bone26",
        "parent": "juguang",
        "x": -32.97,
        "y": 271.96,
        "scaleX": 0.8,
        "scaleY": 0.8
      },
      {
        "name": "bone27",
        "parent": "juguang",
        "x": -49.54,
        "y": -133.26,
        "scaleX": 0.8,
        "scaleY": 0.8
      },
      {
        "name": "bone28",
        "parent": "juguang",
        "x": 129.23,
        "y": 183.18
      },
      {
        "name": "bone29",
        "parent": "juguang",
        "x": -185.35,
        "y": 207.56
      },
      {
        "name": "bone30",
        "parent": "juguang",
        "x": -227.98,
        "y": -51.83
      },
      {
        "name": "bone31",
        "parent": "juguang",
        "x": 148.06,
        "y": -30.4,
        "scaleX": 0.6,
        "scaleY": 0.6
      },
      {
        "name": "bone32",
        "parent": "juguang",
        "x": -183.54,
        "y": 107.79,
        "scaleX": 0.6,
        "scaleY": 0.6
      },
      {
        "name": "bone33",
        "parent": "juguang",
        "x": 74.52,
        "y": -123.82
      },
      {
        "name": "bone34",
        "parent": "juguang",
        "x": -124.58,
        "y": -75.41,
        "scaleX": 0.6,
        "scaleY": 0.6
      },
      {
        "name": "bone35",
        "parent": "juguang",
        "x": 51.37,
        "y": 216.63,
        "scaleX": 0.6,
        "scaleY": 0.6
      },
      {
        "name": "juxian",
        "parent": "bone",
        "x": -44.36,
        "y": 37.17,
        "scaleX": 4,
        "scaleY": 4
      },
      {
        "name": "bone36",
        "parent": "juxian",
        "x": -8.24,
        "y": 9.94
      },
      {
        "name": "bone37",
        "parent": "juxian",
        "rotation": 90,
        "x": -8.24,
        "y": 9.94
      },
      {
        "name": "bone38",
        "parent": "juxian",
        "rotation": 45,
        "x": -8.24,
        "y": 9.94
      },
      {
        "name": "bone39",
        "parent": "juxian",
        "rotation": -45,
        "x": -8.24,
        "y": 9.94
      },
      {
        "name": "bone40",
        "parent": "juxian",
        "rotation": 45,
        "x": -8.24,
        "y": 9.94
      },
      {
        "name": "bone41",
        "parent": "juxian",
        "rotation": -45,
        "x": -8.24,
        "y": 9.94
      },
      {
        "name": "bone42",
        "parent": "juxian",
        "rotation": 90,
        "x": -8.24,
        "y": 9.94
      },
      {
        "name": "bone44",
        "parent": "juxian",
        "rotation": -20,
        "x": -8.24,
        "y": 9.94
      },
      {
        "name": "bone45",
        "parent": "juxian",
        "rotation": 65,
        "x": -8.24,
        "y": 9.94
      },
      {
        "name": "bone47",
        "parent": "juxian",
        "x": -8.24,
        "y": 9.94
      },
      {
        "name": "bone48",
        "parent": "juxian",
        "x": -8.24,
        "y": 9.94
      },
      {
        "name": "bone49",
        "parent": "juxian",
        "x": -8.24,
        "y": 9.94
      },
      {
        "name": "bone50",
        "parent": "juxian",
        "x": -8.24,
        "y": 9.94
      },
      {
        "name": "guangzhu",
        "parent": "shengjiel"
      },
      {
        "name": "fazhen",
        "parent": "guangzhu"
      },
      {
        "name": "bone4",
        "parent": "fazhen"
      },
      {
        "name": "bone6",
        "parent": "fazhen"
      },
      {
        "name": "bone7",
        "parent": "fazhen"
      },
      {
        "name": "xian",
        "parent": "guangzhu"
      },
      {
        "name": "bone10",
        "parent": "xian",
        "x": -16.58
      },
      {
        "name": "bone11",
        "parent": "xian",
        "x": 21.54
      },
      {
        "name": "bone12",
        "parent": "xian",
        "x": 50.15
      },
      {
        "name": "bone20",
        "parent": "xian",
        "x": 86.03
      },
      {
        "name": "bone5",
        "parent": "xian",
        "x": -99.52
      },
      {
        "name": "bone8",
        "parent": "xian",
        "x": -72.73
      },
      {
        "name": "bone9",
        "parent": "xian",
        "x": -44.65
      },
      {
        "name": "xing",
        "parent": "guangzhu"
      },
      {
        "name": "bone13",
        "parent": "xing",
        "x": -111.01,
        "scaleX": 0.6,
        "scaleY": 0.6
      },
      {
        "name": "bone14",
        "parent": "xing",
        "x": -62.52
      },
      {
        "name": "bone15",
        "parent": "xing",
        "x": -24.24,
        "scaleX": 0.6,
        "scaleY": 0.6
      },
      {
        "name": "bone16",
        "parent": "xing",
        "x": 7.65
      },
      {
        "name": "bone17",
        "parent": "xing",
        "x": 43.13,
        "scaleX": 0.8,
        "scaleY": 0.8
      },
      {
        "name": "bone18",
        "parent": "xing",
        "x": 75.28
      },
      {
        "name": "bone19",
        "parent": "xing",
        "x": 121.22,
        "scaleX": 0.6,
        "scaleY": 0.6
      },
      {
        "name": "zhu",
        "parent": "guangzhu",
        "y": 103.35
      }
    ],
    "slots": [
      {
        "name": "juguang01",
        "bone": "bone3",
        "attachment": "juguangdian"
      },
      {
        "name": "guangzhu",
        "bone": "zhu",
        "attachment": "guangzhu"
      },
      {
        "name": "fazhen02",
        "bone": "bone6",
        "attachment": "fazhen02"
      },
      {
        "name": "juguang02",
        "bone": "bone23",
        "attachment": "juguangdian02",
        "blend": "additive"
      },
      {
        "name": "juxing01",
        "bone": "bone24",
        "attachment": "xingxing",
        "blend": "additive"
      },
      {
        "name": "juxing02",
        "bone": "bone25",
        "attachment": "xingxing",
        "blend": "additive"
      },
      {
        "name": "juxing03",
        "bone": "bone26",
        "attachment": "xingxing",
        "blend": "additive"
      },
      {
        "name": "juxing04",
        "bone": "bone27",
        "attachment": "xingxing",
        "blend": "additive"
      },
      {
        "name": "juxing05",
        "bone": "bone28",
        "attachment": "xingxing",
        "blend": "additive"
      },
      {
        "name": "juxing06",
        "bone": "bone29",
        "attachment": "xingxing",
        "blend": "additive"
      },
      {
        "name": "juxing07",
        "bone": "bone30",
        "attachment": "xingxing",
        "blend": "additive"
      },
      {
        "name": "juxing08",
        "bone": "bone31",
        "attachment": "xingxing",
        "blend": "additive"
      },
      {
        "name": "juxing09",
        "bone": "bone32",
        "attachment": "xingxing",
        "blend": "additive"
      },
      {
        "name": "juxing10",
        "bone": "bone33",
        "attachment": "xingxing",
        "blend": "additive"
      },
      {
        "name": "juxing11",
        "bone": "bone34",
        "attachment": "xingxing",
        "blend": "additive"
      },
      {
        "name": "juxing12",
        "bone": "bone35",
        "attachment": "xingxing",
        "blend": "additive"
      },
      {
        "name": "xian01",
        "bone": "bone36",
        "attachment": "guangxian",
        "blend": "additive"
      },
      {
        "name": "xian02",
        "bone": "bone37",
        "attachment": "guangxian",
        "blend": "additive"
      },
      {
        "name": "xian03",
        "bone": "bone38",
        "attachment": "guangxian",
        "blend": "additive"
      },
      {
        "name": "xian04",
        "bone": "bone39",
        "attachment": "guangxian",
        "blend": "additive"
      },
      {
        "name": "xian05",
        "bone": "bone40",
        "attachment": "guangxian",
        "blend": "additive"
      },
      {
        "name": "xian06",
        "bone": "bone41",
        "attachment": "guangxian",
        "blend": "additive"
      },
      {
        "name": "xian07",
        "bone": "bone42",
        "attachment": "guangxian",
        "blend": "additive"
      },
      {
        "name": "xian09",
        "bone": "bone44",
        "attachment": "guangxian",
        "blend": "additive"
      },
      {
        "name": "xian10",
        "bone": "bone45",
        "attachment": "guangxian",
        "blend": "additive"
      },
      {
        "name": "xian12",
        "bone": "bone47",
        "attachment": "guangxian",
        "blend": "additive"
      },
      {
        "name": "xian13",
        "bone": "bone48",
        "attachment": "guangxian",
        "blend": "additive"
      },
      {
        "name": "xian14",
        "bone": "bone49",
        "attachment": "guangxian",
        "blend": "additive"
      },
      {
        "name": "xian15",
        "bone": "bone50",
        "attachment": "guangxian",
        "blend": "additive"
      },
      {
        "name": "guangquan",
        "bone": "bone2",
        "attachment": "guangquan",
        "blend": "additive"
      },
      {
        "name": "fazhen01",
        "bone": "bone4",
        "attachment": "fazhen01",
        "blend": "additive"
      },
      {
        "name": "fazhen03",
        "bone": "bone7",
        "attachment": "fazhen03",
        "blend": "additive"
      },
      {
        "name": "guangxian01",
        "bone": "bone5",
        "attachment": "guangxian02",
        "blend": "additive"
      },
      {
        "name": "guangxian02",
        "bone": "bone8",
        "attachment": "guangxian02",
        "blend": "additive"
      },
      {
        "name": "guangxian03",
        "bone": "bone9",
        "attachment": "guangxian02",
        "blend": "additive"
      },
      {
        "name": "guangxian04",
        "bone": "bone10",
        "attachment": "guangxian02",
        "blend": "additive"
      },
      {
        "name": "guangxian05",
        "bone": "bone11",
        "attachment": "guangxian02",
        "blend": "additive"
      },
      {
        "name": "guangxian06",
        "bone": "bone12",
        "attachment": "guangxian02",
        "blend": "additive"
      },
      {
        "name": "guangxian07",
        "bone": "bone20",
        "attachment": "guangxian02",
        "blend": "additive"
      },
      {
        "name": "xing01",
        "bone": "bone13",
        "attachment": "xingxing",
        "blend": "additive"
      },
      {
        "name": "xing02",
        "bone": "bone14",
        "attachment": "xingxing",
        "blend": "additive"
      },
      {
        "name": "xing03",
        "bone": "bone15",
        "attachment": "xingxing",
        "blend": "additive"
      },
      {
        "name": "xing04",
        "bone": "bone16",
        "attachment": "xingxing",
        "blend": "additive"
      },
      {
        "name": "xing05",
        "bone": "bone17",
        "attachment": "xingxing",
        "blend": "additive"
      },
      {
        "name": "xing06",
        "bone": "bone18",
        "attachment": "xingxing",
        "blend": "additive"
      },
      {
        "name": "xing07",
        "bone": "bone19",
        "attachment": "xingxing",
        "blend": "additive"
      }
    ],
    "skins": [
      {
        "name": "default",
        "attachments": {
          "fazhen01": {
            "fazhen01": {
              "width": 120,
              "height": 59
            }
          },
          "fazhen02": {
            "fazhen02": {
              "width": 160,
              "height": 93
            }
          },
          "fazhen03": {
            "fazhen03": {
              "width": 160,
              "height": 93
            }
          },
          "guangquan": {
            "guangquan": {
              "width": 160,
              "height": 160
            }
          },
          "guangxian01": {
            "guangxian02": {
              "width": 20,
              "height": 280
            }
          },
          "guangxian02": {
            "guangxian02": {
              "width": 20,
              "height": 280
            }
          },
          "guangxian03": {
            "guangxian02": {
              "width": 20,
              "height": 280
            }
          },
          "guangxian04": {
            "guangxian02": {
              "width": 20,
              "height": 280
            }
          },
          "guangxian05": {
            "guangxian02": {
              "width": 20,
              "height": 280
            }
          },
          "guangxian06": {
            "guangxian02": {
              "width": 20,
              "height": 280
            }
          },
          "guangxian07": {
            "guangxian02": {
              "width": 20,
              "height": 280
            }
          },
          "guangzhu": {
            "guangzhu": {
              "width": 140,
              "height": 300
            }
          },
          "juguang01": {
            "juguangdian": {
              "width": 120,
              "height": 120
            }
          },
          "juguang02": {
            "juguangdian02": {
              "width": 120,
              "height": 120
            }
          },
          "juxing01": {
            "xingxing": {
              "width": 60,
              "height": 60
            }
          },
          "juxing02": {
            "xingxing": {
              "width": 60,
              "height": 60
            }
          },
          "juxing03": {
            "xingxing": {
              "width": 60,
              "height": 60
            }
          },
          "juxing04": {
            "xingxing": {
              "width": 60,
              "height": 60
            }
          },
          "juxing05": {
            "xingxing": {
              "width": 60,
              "height": 60
            }
          },
          "juxing06": {
            "xingxing": {
              "width": 60,
              "height": 60
            }
          },
          "juxing07": {
            "xingxing": {
              "width": 60,
              "height": 60
            }
          },
          "juxing08": {
            "xingxing": {
              "width": 60,
              "height": 60
            }
          },
          "juxing09": {
            "xingxing": {
              "width": 60,
              "height": 60
            }
          },
          "juxing10": {
            "xingxing": {
              "width": 60,
              "height": 60
            }
          },
          "juxing11": {
            "xingxing": {
              "width": 60,
              "height": 60
            }
          },
          "juxing12": {
            "xingxing": {
              "width": 60,
              "height": 60
            }
          },
          "xian01": {
            "guangxian": {
              "scaleX": 0.25,
              "scaleY": 0.25,
              "width": 40,
              "height": 200
            }
          },
          "xian02": {
            "guangxian": {
              "scaleX": 0.25,
              "scaleY": 0.25,
              "width": 40,
              "height": 200
            }
          },
          "xian03": {
            "guangxian": {
              "scaleX": 0.25,
              "scaleY": 0.25,
              "width": 40,
              "height": 200
            }
          },
          "xian04": {
            "guangxian": {
              "scaleX": 0.25,
              "scaleY": 0.25,
              "width": 40,
              "height": 200
            }
          },
          "xian05": {
            "guangxian": {
              "scaleX": 0.25,
              "scaleY": 0.25,
              "width": 40,
              "height": 200
            }
          },
          "xian06": {
            "guangxian": {
              "scaleX": 0.25,
              "scaleY": 0.25,
              "width": 40,
              "height": 200
            }
          },
          "xian07": {
            "guangxian": {
              "scaleX": 0.25,
              "scaleY": 0.25,
              "width": 40,
              "height": 200
            }
          },
          "xian09": {
            "guangxian": {
              "scaleX": 0.25,
              "scaleY": 0.25,
              "width": 40,
              "height": 200
            }
          },
          "xian10": {
            "guangxian": {
              "scaleX": 0.25,
              "scaleY": 0.25,
              "width": 40,
              "height": 200
            }
          },
          "xian12": {
            "guangxian": {
              "scaleX": 0.25,
              "scaleY": 0.25,
              "width": 40,
              "height": 200
            }
          },
          "xian13": {
            "guangxian": {
              "scaleX": 0.25,
              "scaleY": 0.25,
              "width": 40,
              "height": 200
            }
          },
          "xian14": {
            "guangxian": {
              "scaleX": 0.25,
              "scaleY": 0.25,
              "width": 40,
              "height": 200
            }
          },
          "xian15": {
            "guangxian": {
              "scaleX": 0.25,
              "scaleY": 0.25,
              "width": 40,
              "height": 200
            }
          },
          "xing01": {
            "xingxing": {
              "width": 60,
              "height": 60
            }
          },
          "xing02": {
            "xingxing": {
              "width": 60,
              "height": 60
            }
          },
          "xing03": {
            "xingxing": {
              "width": 60,
              "height": 60
            }
          },
          "xing04": {
            "xingxing": {
              "width": 60,
              "height": 60
            }
          },
          "xing05": {
            "xingxing": {
              "width": 60,
              "height": 60
            }
          },
          "xing06": {
            "xingxing": {
              "width": 60,
              "height": 60
            }
          },
          "xing07": {
            "xingxing": {
              "width": 60,
              "height": 60
            }
          }
        }
      }
    ],
    "animations": {
      "animation": {
        "slots": {
          "fazhen01": {
            "color": [
              {
                "time": 0.8333,
                "color": "ffffff00"
              },
              {
                "time": 1,
                "color": "ffffffff",
                "curve": "stepped"
              },
              {
                "time": 1.5,
                "color": "ffffffff"
              },
              {
                "time": 1.8333,
                "color": "ffffff00"
              }
            ],
            "attachment": [
              {
                "name": null
              },
              {
                "time": 0.8333,
                "name": "fazhen01"
              }
            ]
          },
          "fazhen02": {
            "color": [
              {
                "time": 0.8333,
                "color": "ffffff00"
              },
              {
                "time": 1,
                "color": "ffffffff",
                "curve": "stepped"
              },
              {
                "time": 1.5,
                "color": "ffffffff"
              },
              {
                "time": 1.8333,
                "color": "ffffff00"
              }
            ],
            "attachment": [
              {
                "name": null
              },
              {
                "time": 0.8333,
                "name": "fazhen02"
              }
            ]
          },
          "fazhen03": {
            "color": [
              {
                "time": 0.8333,
                "color": "ffffff00"
              },
              {
                "time": 1,
                "color": "ffffffff",
                "curve": "stepped"
              },
              {
                "time": 1.5,
                "color": "ffffffff"
              },
              {
                "time": 1.8333,
                "color": "ffffff00"
              }
            ],
            "attachment": [
              {
                "name": null
              },
              {
                "time": 0.8333,
                "name": "fazhen03"
              }
            ]
          },
          "guangquan": {
            "color": [
              {
                "time": 0.3,
                "color": "ffffff00"
              },
              {
                "time": 0.6333,
                "color": "ffffffff"
              },
              {
                "time": 0.9667,
                "color": "ffffff00"
              }
            ],
            "attachment": [
              {
                "name": null
              },
              {
                "time": 0.3,
                "name": "guangquan"
              }
            ]
          },
          "guangxian01": {
            "color": [
              {
                "time": 0.8333,
                "color": "ffffff00"
              },
              {
                "time": 1,
                "color": "ffffffff",
                "curve": "stepped"
              },
              {
                "time": 1.1667,
                "color": "ffffffff"
              },
              {
                "time": 1.3333,
                "color": "ffffff00"
              }
            ],
            "attachment": [
              {
                "name": null
              },
              {
                "time": 0.8333,
                "name": "guangxian02"
              }
            ]
          },
          "guangxian02": {
            "color": [
              {
                "time": 1.1667,
                "color": "ffffff00"
              },
              {
                "time": 1.3333,
                "color": "ffffffff",
                "curve": "stepped"
              },
              {
                "time": 1.5,
                "color": "ffffffff"
              },
              {
                "time": 1.6667,
                "color": "ffffff00"
              }
            ],
            "attachment": [
              {
                "name": null
              },
              {
                "time": 1.1667,
                "name": "guangxian02"
              }
            ]
          },
          "guangxian03": {
            "color": [
              {
                "time": 1,
                "color": "ffffff00"
              },
              {
                "time": 1.1667,
                "color": "ffffffff",
                "curve": "stepped"
              },
              {
                "time": 1.3333,
                "color": "ffffffff"
              },
              {
                "time": 1.5,
                "color": "ffffff00"
              }
            ],
            "attachment": [
              {
                "name": null
              },
              {
                "time": 1,
                "name": "guangxian02"
              }
            ]
          },
          "guangxian04": {
            "color": [
              {
                "time": 1.1,
                "color": "ffffff00"
              },
              {
                "time": 1.2667,
                "color": "ffffffff",
                "curve": "stepped"
              },
              {
                "time": 1.4333,
                "color": "ffffffff"
              },
              {
                "time": 1.6,
                "color": "ffffff00"
              }
            ],
            "attachment": [
              {
                "name": null
              },
              {
                "time": 1.1,
                "name": "guangxian02"
              }
            ]
          },
          "guangxian05": {
            "color": [
              {
                "time": 1.3333,
                "color": "ffffff00"
              },
              {
                "time": 1.5,
                "color": "ffffffff",
                "curve": "stepped"
              },
              {
                "time": 1.6667,
                "color": "ffffffff"
              },
              {
                "time": 1.8333,
                "color": "ffffff00"
              }
            ],
            "attachment": [
              {
                "name": null
              },
              {
                "time": 1.3333,
                "name": "guangxian02"
              }
            ]
          },
          "guangxian06": {
            "color": [
              {
                "time": 0.9,
                "color": "ffffff00"
              },
              {
                "time": 1.0667,
                "color": "ffffffff",
                "curve": "stepped"
              },
              {
                "time": 1.2333,
                "color": "ffffffff"
              },
              {
                "time": 1.4,
                "color": "ffffff00"
              }
            ],
            "attachment": [
              {
                "name": null
              },
              {
                "time": 0.9,
                "name": "guangxian02"
              }
            ]
          },
          "guangxian07": {
            "color": [
              {
                "time": 1.1667,
                "color": "ffffff00"
              },
              {
                "time": 1.3333,
                "color": "ffffffff",
                "curve": "stepped"
              },
              {
                "time": 1.5,
                "color": "ffffffff"
              },
              {
                "time": 1.6667,
                "color": "ffffff00"
              }
            ],
            "attachment": [
              {
                "name": null
              },
              {
                "time": 1.1667,
                "name": "guangxian02"
              }
            ]
          },
          "guangzhu": {
            "color": [
              {
                "time": 1.6667,
                "color": "ffffffff"
              },
              {
                "time": 1.8333,
                "color": "ffffff00"
              }
            ],
            "attachment": [
              {
                "name": null
              },
              {
                "time": 0.8333,
                "name": "guangzhu"
              }
            ]
          },
          "juguang01": {
            "color": [
              {
                "time": 0.3,
                "color": "ffffff00"
              },
              {
                "time": 0.3667,
                "color": "ffffffff",
                "curve": "stepped"
              },
              {
                "time": 0.7667,
                "color": "ffffffff"
              },
              {
                "time": 0.9333,
                "color": "ffffff00"
              }
            ],
            "attachment": [
              {
                "name": null
              },
              {
                "time": 0.3,
                "name": "juguangdian"
              }
            ]
          },
          "juguang02": {
            "color": [
              {
                "time": 0.3333,
                "color": "ffffff39"
              },
              {
                "time": 0.5,
                "color": "ffffffff",
                "curve": "stepped"
              },
              {
                "time": 0.7333,
                "color": "ffffffff"
              },
              {
                "time": 0.9333,
                "color": "ffffff00"
              }
            ],
            "attachment": [
              {
                "name": null
              },
              {
                "time": 0.3333,
                "name": "juguangdian02"
              },
              {
                "time": 0.9333,
                "name": null
              }
            ]
          },
          "juxing01": {
            "color": [
              {
                "time": 0.4333,
                "color": "ffffff64"
              },
              {
                "time": 0.5,
                "color": "ffffffff",
                "curve": "stepped"
              },
              {
                "time": 0.6,
                "color": "ffffffff"
              },
              {
                "time": 0.6667,
                "color": "ffffff00"
              }
            ],
            "attachment": [
              {
                "name": null
              },
              {
                "time": 0.4333,
                "name": "xingxing"
              },
              {
                "time": 0.6667,
                "name": null
              }
            ]
          },
          "juxing02": {
            "color": [
              {
                "time": 0.6667,
                "color": "ffffff64"
              },
              {
                "time": 0.7333,
                "color": "ffffffff",
                "curve": "stepped"
              },
              {
                "time": 0.8333,
                "color": "ffffffff"
              },
              {
                "time": 0.9,
                "color": "ffffff00"
              }
            ],
            "attachment": [
              {
                "name": null
              },
              {
                "time": 0.6667,
                "name": "xingxing"
              },
              {
                "time": 0.9,
                "name": null
              }
            ]
          },
          "juxing03": {
            "color": [
              {
                "time": 0.4,
                "color": "ffffff64"
              },
              {
                "time": 0.4667,
                "color": "ffffffff",
                "curve": "stepped"
              },
              {
                "time": 0.5333,
                "color": "ffffffff"
              },
              {
                "time": 0.6,
                "color": "ffffff00"
              }
            ],
            "attachment": [
              {
                "name": null
              },
              {
                "time": 0.4,
                "name": "xingxing"
              },
              {
                "time": 0.6,
                "name": null
              }
            ]
          },
          "juxing04": {
            "color": [
              {
                "time": 0.5667,
                "color": "ffffff64"
              },
              {
                "time": 0.6333,
                "color": "ffffffff",
                "curve": "stepped"
              },
              {
                "time": 0.7333,
                "color": "ffffffff"
              },
              {
                "time": 0.8,
                "color": "ffffff00"
              }
            ],
            "attachment": [
              {
                "name": null
              },
              {
                "time": 0.5667,
                "name": "xingxing"
              },
              {
                "time": 0.8,
                "name": null
              }
            ]
          },
          "juxing05": {
            "color": [
              {
                "time": 0.3,
                "color": "ffffff64"
              },
              {
                "time": 0.3667,
                "color": "ffffffff",
                "curve": "stepped"
              },
              {
                "time": 0.5,
                "color": "ffffffff"
              },
              {
                "time": 0.5667,
                "color": "ffffff00"
              }
            ],
            "attachment": [
              {
                "name": null
              },
              {
                "time": 0.3,
                "name": "xingxing"
              },
              {
                "time": 0.5667,
                "name": null
              }
            ]
          },
          "juxing06": {
            "color": [
              {
                "time": 0.6,
                "color": "ffffff64"
              },
              {
                "time": 0.6667,
                "color": "ffffffff",
                "curve": "stepped"
              },
              {
                "time": 0.7667,
                "color": "ffffffff"
              },
              {
                "time": 0.8333,
                "color": "ffffff00"
              }
            ],
            "attachment": [
              {
                "name": null
              },
              {
                "time": 0.6,
                "name": "xingxing"
              },
              {
                "time": 0.8333,
                "name": null
              }
            ]
          },
          "juxing07": {
            "color": [
              {
                "time": 0.7,
                "color": "ffffff64"
              },
              {
                "time": 0.7667,
                "color": "ffffffff",
                "curve": "stepped"
              },
              {
                "time": 0.8333,
                "color": "ffffffff"
              },
              {
                "time": 0.9,
                "color": "ffffff00"
              }
            ],
            "attachment": [
              {
                "name": null
              },
              {
                "time": 0.7,
                "name": "xingxing"
              },
              {
                "time": 0.9,
                "name": null
              }
            ]
          },
          "juxing08": {
            "color": [
              {
                "time": 0.6667,
                "color": "ffffff64"
              },
              {
                "time": 0.7333,
                "color": "ffffffff",
                "curve": "stepped"
              },
              {
                "time": 0.8667,
                "color": "ffffffff"
              },
              {
                "time": 0.9333,
                "color": "ffffff00"
              }
            ],
            "attachment": [
              {
                "name": null
              },
              {
                "time": 0.6667,
                "name": "xingxing"
              },
              {
                "time": 0.9333,
                "name": null
              }
            ]
          },
          "juxing09": {
            "color": [
              {
                "time": 0.7333,
                "color": "ffffff64"
              },
              {
                "time": 0.8,
                "color": "ffffffff",
                "curve": "stepped"
              },
              {
                "time": 0.8667,
                "color": "ffffffff"
              },
              {
                "time": 0.9333,
                "color": "ffffff00"
              }
            ],
            "attachment": [
              {
                "name": null
              },
              {
                "time": 0.7333,
                "name": "xingxing"
              }
            ]
          },
          "juxing10": {
            "color": [
              {
                "time": 0.4,
                "color": "ffffff64"
              },
              {
                "time": 0.4667,
                "color": "ffffffff",
                "curve": "stepped"
              },
              {
                "time": 0.5667,
                "color": "ffffffff"
              },
              {
                "time": 0.6333,
                "color": "ffffff00"
              }
            ],
            "attachment": [
              {
                "name": null
              },
              {
                "time": 0.4,
                "name": "xingxing"
              },
              {
                "time": 0.6333,
                "name": null
              }
            ]
          },
          "juxing11": {
            "color": [
              {
                "time": 0.3333,
                "color": "ffffff64"
              },
              {
                "time": 0.4,
                "color": "ffffffff",
                "curve": "stepped"
              },
              {
                "time": 0.5,
                "color": "ffffffff"
              },
              {
                "time": 0.5667,
                "color": "ffffff00"
              }
            ],
            "attachment": [
              {
                "name": null
              },
              {
                "time": 0.3333,
                "name": "xingxing"
              }
            ]
          },
          "juxing12": {
            "color": [
              {
                "time": 0.5,
                "color": "ffffff64"
              },
              {
                "time": 0.5667,
                "color": "ffffffff",
                "curve": "stepped"
              },
              {
                "time": 0.6667,
                "color": "ffffffff"
              },
              {
                "time": 0.7333,
                "color": "ffffff00"
              }
            ],
            "attachment": [
              {
                "name": null
              },
              {
                "time": 0.5,
                "name": "xingxing"
              }
            ]
          },
          "xian01": {
            "color": [
              {
                "time": 0.6,
                "color": "ffffff00"
              },
              {
                "time": 0.7667,
                "color": "ffffffff"
              },
              {
                "time": 0.9333,
                "color": "ffffff00"
              }
            ],
            "attachment": [
              {
                "name": null
              },
              {
                "time": 0.6,
                "name": "guangxian"
              }
            ]
          },
          "xian02": {
            "color": [
              {
                "time": 0.6,
                "color": "ffffff00"
              },
              {
                "time": 0.7667,
                "color": "ffffffff"
              },
              {
                "time": 0.9333,
                "color": "ffffff00"
              }
            ],
            "attachment": [
              {
                "name": null
              },
              {
                "time": 0.6,
                "name": "guangxian"
              },
              {
                "time": 0.9333,
                "name": null
              }
            ]
          },
          "xian03": {
            "color": [
              {
                "time": 0.4333,
                "color": "ffffff00"
              },
              {
                "time": 0.6,
                "color": "ffffffff"
              },
              {
                "time": 0.7667,
                "color": "ffffff00"
              }
            ],
            "attachment": [
              {
                "name": null
              },
              {
                "time": 0.4333,
                "name": "guangxian"
              },
              {
                "time": 0.7667,
                "name": null
              }
            ]
          },
          "xian04": {
            "color": [
              {
                "time": 0.2667,
                "color": "ffffff00"
              },
              {
                "time": 0.4333,
                "color": "ffffffff"
              },
              {
                "time": 0.6,
                "color": "ffffff00"
              }
            ],
            "attachment": [
              {
                "name": null
              },
              {
                "time": 0.2667,
                "name": "guangxian"
              },
              {
                "time": 0.6,
                "name": null
              }
            ]
          },
          "xian05": {
            "color": [
              {
                "time": 0.2667,
                "color": "ffffff00"
              },
              {
                "time": 0.4333,
                "color": "ffffffff"
              },
              {
                "time": 0.6,
                "color": "ffffff00"
              }
            ],
            "attachment": [
              {
                "name": null
              },
              {
                "time": 0.2667,
                "name": "guangxian"
              },
              {
                "time": 0.6,
                "name": null
              }
            ]
          },
          "xian06": {
            "color": [
              {
                "time": 0.6333,
                "color": "ffffff00"
              },
              {
                "time": 0.8,
                "color": "ffffffff"
              },
              {
                "time": 0.9667,
                "color": "ffffff00"
              }
            ],
            "attachment": [
              {
                "name": null
              },
              {
                "time": 0.6333,
                "name": "guangxian"
              }
            ]
          },
          "xian07": {
            "color": [
              {
                "time": 0.2667,
                "color": "ffffff00"
              },
              {
                "time": 0.4333,
                "color": "ffffffff"
              },
              {
                "time": 0.6,
                "color": "ffffff00"
              }
            ],
            "attachment": [
              {
                "name": null
              },
              {
                "time": 0.2667,
                "name": "guangxian"
              },
              {
                "time": 0.6,
                "name": null
              }
            ]
          },
          "xian09": {
            "color": [
              {
                "time": 0.4667,
                "color": "ffffff00"
              },
              {
                "time": 0.6333,
                "color": "ffffffff"
              },
              {
                "time": 0.8,
                "color": "ffffff00"
              }
            ],
            "attachment": [
              {
                "name": null
              },
              {
                "time": 0.4667,
                "name": "guangxian"
              }
            ]
          },
          "xian10": {
            "color": [
              {
                "time": 0.4667,
                "color": "ffffff00"
              },
              {
                "time": 0.6333,
                "color": "ffffffff"
              },
              {
                "time": 0.8,
                "color": "ffffff00"
              }
            ],
            "attachment": [
              {
                "name": null
              },
              {
                "time": 0.4667,
                "name": "guangxian"
              }
            ]
          },
          "xian12": {
            "color": [
              {
                "time": 0.4333,
                "color": "ffffff00"
              },
              {
                "time": 0.6,
                "color": "ffffffff"
              },
              {
                "time": 0.7667,
                "color": "ffffff00"
              }
            ],
            "attachment": [
              {
                "name": null
              },
              {
                "time": 0.4333,
                "name": "guangxian"
              },
              {
                "time": 0.7667,
                "name": null
              }
            ]
          },
          "xian13": {
            "color": [
              {
                "time": 0.6,
                "color": "ffffff00"
              },
              {
                "time": 0.7667,
                "color": "ffffffff"
              },
              {
                "time": 0.9333,
                "color": "ffffff00"
              }
            ],
            "attachment": [
              {
                "name": null
              },
              {
                "time": 0.6,
                "name": "guangxian"
              }
            ]
          },
          "xian14": {
            "color": [
              {
                "time": 0.5667,
                "color": "ffffff00"
              },
              {
                "time": 0.7333,
                "color": "ffffffff"
              },
              {
                "time": 0.9,
                "color": "ffffff00"
              }
            ],
            "attachment": [
              {
                "name": null
              },
              {
                "time": 0.5667,
                "name": "guangxian"
              }
            ]
          },
          "xian15": {
            "color": [
              {
                "time": 0.6,
                "color": "ffffff00"
              },
              {
                "time": 0.7667,
                "color": "ffffffff"
              },
              {
                "time": 0.9333,
                "color": "ffffff00"
              }
            ],
            "attachment": [
              {
                "name": null
              },
              {
                "time": 0.6,
                "name": "guangxian"
              }
            ]
          },
          "xing01": {
            "color": [
              {
                "time": 0.8333,
                "color": "ffffff00"
              },
              {
                "time": 1,
                "color": "ffffffff",
                "curve": "stepped"
              },
              {
                "time": 1.1667,
                "color": "ffffffff"
              },
              {
                "time": 1.3333,
                "color": "ffffff00"
              }
            ],
            "attachment": [
              {
                "name": null
              },
              {
                "time": 0.8333,
                "name": "xingxing"
              }
            ]
          },
          "xing02": {
            "color": [
              {
                "time": 1.3333,
                "color": "ffffff00"
              },
              {
                "time": 1.5,
                "color": "ffffffff",
                "curve": "stepped"
              },
              {
                "time": 1.6667,
                "color": "ffffffff"
              },
              {
                "time": 1.8333,
                "color": "ffffff00"
              }
            ],
            "attachment": [
              {
                "name": null
              },
              {
                "time": 1.3333,
                "name": "xingxing"
              }
            ]
          },
          "xing03": {
            "color": [
              {
                "time": 1,
                "color": "ffffff00"
              },
              {
                "time": 1.1667,
                "color": "ffffffff",
                "curve": "stepped"
              },
              {
                "time": 1.3333,
                "color": "ffffffff"
              },
              {
                "time": 1.5,
                "color": "ffffff00"
              }
            ],
            "attachment": [
              {
                "name": null
              },
              {
                "time": 1,
                "name": "xingxing"
              }
            ]
          },
          "xing04": {
            "color": [
              {
                "time": 1.1667,
                "color": "ffffff00"
              },
              {
                "time": 1.3333,
                "color": "ffffffff",
                "curve": "stepped"
              },
              {
                "time": 1.5,
                "color": "ffffffff"
              },
              {
                "time": 1.6667,
                "color": "ffffff00"
              }
            ],
            "attachment": [
              {
                "name": null
              },
              {
                "time": 1.1667,
                "name": "xingxing"
              }
            ]
          },
          "xing05": {
            "color": [
              {
                "time": 0.9,
                "color": "ffffff00"
              },
              {
                "time": 1.0667,
                "color": "ffffffff",
                "curve": "stepped"
              },
              {
                "time": 1.2333,
                "color": "ffffffff"
              },
              {
                "time": 1.4,
                "color": "ffffff00"
              }
            ],
            "attachment": [
              {
                "name": null
              },
              {
                "time": 0.9,
                "name": "xingxing"
              }
            ]
          },
          "xing06": {
            "color": [
              {
                "time": 1.3333,
                "color": "ffffff00"
              },
              {
                "time": 1.5,
                "color": "ffffffff",
                "curve": "stepped"
              },
              {
                "time": 1.6667,
                "color": "ffffffff"
              },
              {
                "time": 1.8333,
                "color": "ffffff00"
              }
            ],
            "attachment": [
              {
                "name": null
              },
              {
                "time": 1.3333,
                "name": "xingxing"
              }
            ]
          },
          "xing07": {
            "color": [
              {
                "time": 0.9333,
                "color": "ffffff00"
              },
              {
                "time": 1.1,
                "color": "ffffffff",
                "curve": "stepped"
              },
              {
                "time": 1.2667,
                "color": "ffffffff"
              },
              {
                "time": 1.4333,
                "color": "ffffff00"
              }
            ],
            "attachment": [
              {
                "name": null
              },
              {
                "time": 0.9333,
                "name": "xingxing"
              }
            ]
          }
        },
        "bones": {
          "bone4": {
            "scale": [
              {
                "time": 0.8333,
                "x": 0.504,
                "y": 0.5
              },
              {
                "time": 1,
                "x": 1.3,
                "y": 1.3
              },
              {
                "time": 1.1667,
                "x": 1.7,
                "y": 1.7
              },
              {
                "time": 1.3333,
                "x": 1.3,
                "y": 1.3
              },
              {
                "time": 1.5,
                "x": 1.7,
                "y": 1.7
              },
              {
                "time": 1.8333,
                "x": 1.3,
                "y": 1.3
              }
            ]
          },
          "bone6": {
            "scale": [
              {
                "time": 0.8333,
                "x": 0.5,
                "y": 0.5
              },
              {
                "time": 1,
                "x": 1.5,
                "y": 1.5
              },
              {
                "time": 1.1667,
                "x": 1.3,
                "y": 1.3
              },
              {
                "time": 1.3333,
                "x": 1.5,
                "y": 1.5
              },
              {
                "time": 1.5,
                "x": 1.2,
                "y": 1.2
              },
              {
                "time": 1.8333,
                "x": 1.7,
                "y": 1.7
              }
            ]
          },
          "bone7": {
            "scale": [
              {
                "time": 0.8333,
                "x": 0.5,
                "y": 0.5
              },
              {
                "time": 1,
                "x": 1.8,
                "y": 1.8
              },
              {
                "time": 1.1667,
                "x": 1.8,
                "y": 1.594
              },
              {
                "time": 1.3333,
                "x": 2,
                "y": 1.796
              },
              {
                "time": 1.5,
                "x": 1.8,
                "y": 1.617
              },
              {
                "time": 1.8333,
                "x": 2.5,
                "y": 2.2
              }
            ]
          },
          "bone2": {
            "scale": [
              {
                "time": 0.3,
                "x": 3.5,
                "y": 3.5
              },
              {
                "time": 0.6333,
                "x": 2.3,
                "y": 2.3
              },
              {
                "time": 0.9667,
                "x": 0.5,
                "y": 0.5
              }
            ]
          },
          "bone5": {
            "translate": [
              {
                "time": 0.8333,
                "x": 25.07
              },
              {
                "time": 1.3333,
                "x": 25.07,
                "y": 508.8
              }
            ],
            "scale": [
              {
                "time": 0.8333,
                "y": 0.3
              },
              {
                "time": 1,
                "y": 1.8
              },
              {
                "time": 1.3333
              }
            ]
          },
          "bone8": {
            "translate": [
              {
                "time": 1.1667,
                "x": 13.49
              },
              {
                "time": 1.6667,
                "x": 13.49,
                "y": 507.45
              }
            ],
            "scale": [
              {
                "time": 1.1667,
                "y": 0.3
              },
              {
                "time": 1.3333,
                "y": 2.106
              },
              {
                "time": 1.6667
              }
            ]
          },
          "bone9": {
            "translate": [
              {
                "time": 1,
                "x": 9.44
              },
              {
                "time": 1.5,
                "x": 9.44,
                "y": 510.15
              }
            ],
            "scale": [
              {
                "time": 1,
                "y": 0.3
              },
              {
                "time": 1.1667,
                "y": 2.147
              },
              {
                "time": 1.5
              }
            ]
          },
          "bone10": {
            "translate": [
              {
                "time": 1.1
              },
              {
                "time": 1.6,
                "y": 510.15
              }
            ],
            "scale": [
              {
                "time": 1.1,
                "y": 0.3
              },
              {
                "time": 1.2667,
                "y": 2.079
              },
              {
                "time": 1.6
              }
            ]
          },
          "bone11": {
            "translate": [
              {
                "time": 1.3333
              },
              {
                "time": 1.8333,
                "y": 510.15
              }
            ],
            "scale": [
              {
                "time": 1.3333,
                "y": 0.3
              },
              {
                "time": 1.5,
                "y": 1.971
              },
              {
                "time": 1.8333
              }
            ]
          },
          "bone12": {
            "translate": [
              {
                "time": 0.9
              },
              {
                "time": 1.4,
                "y": 510.15
              }
            ],
            "scale": [
              {
                "time": 0.9,
                "y": 0.3
              },
              {
                "time": 1.0667,
                "y": 1.917
              },
              {
                "time": 1.4
              }
            ]
          },
          "bone20": {
            "translate": [
              {
                "time": 1.1667
              },
              {
                "time": 1.6667,
                "y": 508.8
              }
            ],
            "scale": [
              {
                "time": 1.1667,
                "x": 1.013,
                "y": 0.3
              },
              {
                "time": 1.3333,
                "y": 2
              },
              {
                "time": 1.6667
              }
            ]
          },
          "zhu": {
            "translate": [
              {
                "time": 0.8333,
                "y": -85.47
              },
              {
                "time": 1,
                "y": 188.85
              }
            ],
            "scale": [
              {
                "time": 0.8333,
                "x": 0.839,
                "y": 0.238
              },
              {
                "time": 1,
                "x": 2,
                "y": 2.465
              },
              {
                "time": 1.1667,
                "x": 1.6,
                "y": 2.465
              },
              {
                "time": 1.3333,
                "x": 2,
                "y": 2.465
              },
              {
                "time": 1.5,
                "x": 1.6,
                "y": 2.465
              },
              {
                "time": 1.6667,
                "x": 2,
                "y": 2.465
              },
              {
                "time": 1.8333,
                "x": 0.082,
                "y": 2.465
              }
            ]
          },
          "bone3": {
            "scale": [
              {
                "time": 0.3,
                "x": 0.5,
                "y": 0.5
              },
              {
                "time": 0.4667,
                "x": 1.5,
                "y": 1.5
              },
              {
                "time": 0.6333
              },
              {
                "time": 0.7667,
                "x": 1.5,
                "y": 1.5
              },
              {
                "time": 0.9333,
                "x": 0.6,
                "y": 0.6
              }
            ]
          },
          "bone23": {
            "scale": [
              {
                "time": 0.3333,
                "x": 10,
                "y": 10
              },
              {
                "time": 0.6667,
                "x": 4,
                "y": 4
              },
              {
                "time": 0.9333
              }
            ]
          },
          "bone24": {
            "translate": [
              {
                "time": 0.4333
              },
              {
                "time": 0.6667,
                "x": 223.35,
                "y": -19.85
              }
            ]
          },
          "bone25": {
            "translate": [
              {
                "time": 0.6667
              },
              {
                "time": 0.9,
                "x": -220.54,
                "y": -35.37
              }
            ]
          },
          "bone26": {
            "translate": [
              {
                "time": 0.4
              },
              {
                "time": 0.6,
                "x": 0.31,
                "y": -232.37
              }
            ]
          },
          "bone27": {
            "translate": [
              {
                "time": 0.5667
              },
              {
                "time": 0.8,
                "x": 16.87,
                "y": 172.85
              }
            ]
          },
          "bone28": {
            "translate": [
              {
                "time": 0.3
              },
              {
                "time": 0.5667,
                "x": -161.89,
                "y": -143.59
              }
            ]
          },
          "bone29": {
            "translate": [
              {
                "time": 0.6
              },
              {
                "time": 0.8333,
                "x": 152.69,
                "y": -167.97
              }
            ]
          },
          "bone30": {
            "translate": [
              {
                "time": 0.7
              },
              {
                "time": 0.9,
                "x": 195.31,
                "y": 91.42
              }
            ]
          },
          "bone31": {
            "translate": [
              {
                "time": 0.6667,
                "x": -26.28,
                "y": -44.56
              },
              {
                "time": 0.9333,
                "x": -180.72,
                "y": 69.99
              }
            ]
          },
          "bone32": {
            "translate": [
              {
                "time": 0.7333
              },
              {
                "time": 0.9333,
                "x": 150.87,
                "y": -68.2
              }
            ]
          },
          "bone33": {
            "translate": [
              {
                "time": 0.4
              },
              {
                "time": 0.6333,
                "x": -107.18,
                "y": 163.41
              }
            ]
          },
          "bone34": {
            "translate": [
              {
                "time": 0.3333
              },
              {
                "time": 0.5667,
                "x": 91.92,
                "y": 115
              }
            ]
          },
          "bone35": {
            "translate": [
              {
                "time": 0.5
              },
              {
                "time": 0.7333,
                "x": -84.03,
                "y": -177.04
              }
            ]
          },
          "bone36": {
            "translate": [
              {
                "time": 0.6,
                "y": 78.67
              },
              {
                "time": 0.9333
              }
            ],
            "scale": [
              {
                "time": 0.6,
                "y": 1.75
              },
              {
                "time": 0.9333,
                "x": 0.75,
                "y": 0.75
              }
            ]
          },
          "bone37": {
            "translate": [
              {
                "time": 0.6,
                "x": 87.48
              },
              {
                "time": 0.9333
              }
            ],
            "scale": [
              {
                "time": 0.6,
                "y": 1.75
              },
              {
                "time": 0.9333,
                "x": 0.75,
                "y": 0.75
              }
            ]
          },
          "bone38": {
            "translate": [
              {
                "time": 0.4333,
                "x": -55.61,
                "y": 56.58
              },
              {
                "time": 0.7667
              }
            ],
            "scale": [
              {
                "time": 0.4333,
                "y": 1.75
              },
              {
                "time": 0.7667,
                "x": 0.75,
                "y": 0.75
              }
            ]
          },
          "bone39": {
            "translate": [
              {
                "time": 0.2667,
                "x": 58.53,
                "y": 55.28
              },
              {
                "time": 0.6
              }
            ],
            "scale": [
              {
                "time": 0.2667,
                "y": 1.75
              },
              {
                "time": 0.6,
                "x": 0.75,
                "y": 0.75
              }
            ]
          },
          "bone40": {
            "translate": [
              {
                "time": 0.2667,
                "x": 57.23,
                "y": -46.5
              },
              {
                "time": 0.6
              }
            ],
            "scale": [
              {
                "time": 0.2667,
                "y": 1.75
              },
              {
                "time": 0.6,
                "x": 0.75,
                "y": 0.75
              }
            ]
          },
          "bone41": {
            "translate": [
              {
                "time": 0.6333,
                "x": -45.52,
                "y": -42.27
              },
              {
                "time": 0.9667
              }
            ],
            "scale": [
              {
                "time": 0.6333,
                "y": 1.75
              },
              {
                "time": 0.9667,
                "x": 0.75,
                "y": 0.75
              }
            ]
          },
          "bone42": {
            "translate": [
              {
                "time": 0.2667,
                "x": -69.69
              },
              {
                "time": 0.6
              }
            ],
            "scale": [
              {
                "time": 0.2667,
                "y": 1.75
              },
              {
                "time": 0.6,
                "x": 0.75,
                "y": 0.75
              }
            ]
          },
          "bone44": {
            "translate": [
              {
                "time": 0.4667,
                "x": 21.12,
                "y": 49.27
              },
              {
                "time": 0.8,
                "y": 0.35
              }
            ],
            "scale": [
              {
                "time": 0.4667
              },
              {
                "time": 0.8,
                "x": 0.75,
                "y": 0.75
              }
            ]
          },
          "bone45": {
            "translate": [
              {
                "time": 0.4667,
                "x": 57.37,
                "y": -18.3
              },
              {
                "time": 0.8
              }
            ],
            "scale": [
              {
                "time": 0.4667
              },
              {
                "time": 0.8,
                "x": 0.75,
                "y": 0.75
              }
            ]
          },
          "bone47": {
            "translate": [
              {
                "time": 0.4333,
                "y": -61.44
              },
              {
                "time": 0.7667
              }
            ],
            "scale": [
              {
                "time": 0.4333,
                "y": 1.75
              },
              {
                "time": 0.7667,
                "x": 0.75,
                "y": 0.75
              }
            ]
          },
          "bone48": {
            "rotate": [
              {
                "time": 0.6,
                "angle": 78.29
              }
            ],
            "translate": [
              {
                "time": 0.6,
                "x": -50.59,
                "y": 11.7
              },
              {
                "time": 0.9333
              }
            ],
            "scale": [
              {
                "time": 0.6
              },
              {
                "time": 0.9333,
                "x": 0.75,
                "y": 0.75
              }
            ]
          },
          "bone49": {
            "rotate": [
              {
                "time": 0.5667,
                "angle": -53.22
              }
            ],
            "translate": [
              {
                "time": 0.5667,
                "x": 37,
                "y": 24.98
              },
              {
                "time": 0.9
              }
            ],
            "scale": [
              {
                "time": 0.5667
              },
              {
                "time": 0.9,
                "x": 0.75,
                "y": 0.75
              }
            ]
          },
          "bone50": {
            "rotate": [
              {
                "time": 0.6,
                "angle": 24
              }
            ],
            "translate": [
              {
                "time": 0.6,
                "x": 16.12,
                "y": -35.73
              },
              {
                "time": 0.9333
              }
            ],
            "scale": [
              {
                "time": 0.6
              },
              {
                "time": 0.9333,
                "x": 0.5,
                "y": 0.5
              }
            ]
          },
          "bone13": {
            "translate": [
              {
                "time": 0.8333
              },
              {
                "time": 1.3333,
                "y": 520.95
              }
            ]
          },
          "bone14": {
            "translate": [
              {
                "time": 1.3333
              },
              {
                "time": 1.8333,
                "y": 510.15
              }
            ],
            "scale": [
              {
                "time": 1.3333,
                "x": 0.8,
                "y": 0.8
              }
            ]
          },
          "bone15": {
            "translate": [
              {
                "time": 1
              },
              {
                "time": 1.5,
                "y": 511.5
              }
            ]
          },
          "bone16": {
            "translate": [
              {
                "time": 1.1667
              },
              {
                "time": 1.6667,
                "y": 515.55
              }
            ],
            "scale": [
              {
                "time": 1.1667,
                "x": 0.8,
                "y": 0.8
              }
            ]
          },
          "bone17": {
            "translate": [
              {
                "time": 0.9,
                "x": -95.82
              },
              {
                "time": 1.4,
                "x": -95.82,
                "y": 522.3
              }
            ]
          },
          "bone18": {
            "translate": [
              {
                "time": 1.3333
              },
              {
                "time": 1.8333,
                "y": 518.25
              }
            ],
            "scale": [
              {
                "time": 1.3333,
                "x": 0.7,
                "y": 0.7
              }
            ]
          },
          "bone19": {
            "translate": [
              {
                "time": 0.9333,
                "x": -24.29
              },
              {
                "time": 1.4333,
                "x": -24.29,
                "y": 516.9
              }
            ]
          },
          "bone": {
            "translate": [
              {
                "x": 83.95,
                "y": -34.98
              }
            ]
          }
        }
      }
    }
  },
  "_atlasText": "\nsjgx2.png\nsize: 411,290\nformat: RGBA8888\nfilter: Linear,Linear\nrepeat: none\nfazhen01\n  rotate: true\n  xy: 229, 2\n  size: 101, 48\n  orig: 120, 59\n  offset: 9, 5\n  index: -1\nfazhen02\n  rotate: true\n  xy: 152, 6\n  size: 153, 75\n  orig: 160, 93\n  offset: 3, 9\n  index: -1\nfazhen03\n  rotate: true\n  xy: 329, 39\n  size: 141, 80\n  orig: 160, 93\n  offset: 10, 6\n  index: -1\nguangquan\n  rotate: false\n  xy: 2, 11\n  size: 148, 148\n  orig: 160, 160\n  offset: 5, 6\n  index: -1\nguangxian\n  rotate: false\n  xy: 300, 16\n  size: 27, 164\n  orig: 40, 200\n  offset: 6, 18\n  index: -1\nguangxian02\n  rotate: false\n  xy: 289, 26\n  size: 9, 262\n  orig: 20, 280\n  offset: 6, 9\n  index: -1\nguangzhu\n  rotate: true\n  xy: 2, 161\n  size: 127, 285\n  orig: 140, 300\n  offset: 7, 15\n  index: -1\njuguangdian\n  rotate: true\n  xy: 300, 182\n  size: 106, 104\n  orig: 120, 120\n  offset: 7, 8\n  index: -1\njuguangdian02\n  rotate: true\n  xy: 300, 182\n  size: 106, 104\n  orig: 120, 120\n  offset: 7, 8\n  index: -1\nxingxing\n  rotate: false\n  xy: 229, 105\n  size: 54, 54\n  orig: 60, 60\n  offset: 3, 2\n  index: -1\n",
  "textures": [
    {
      "__uuid__": "72674459-fb16-4716-99b5-719333962dde"
    }
  ],
  "textureNames": [
    "sjgx2.png"
  ],
  "scale": 1
}